[
  {
    "model": "persistent_message.taggroup",
    "pk": 1,
    "fields": {
      "name": "Campuses"
    }
  },
  {
    "model": "persistent_message.tag",
    "pk": 1,
    "fields": {
      "name": "seattle",
      "group": 1
    }
  },
  {
    "model": "persistent_message.tag",
    "pk": 2,
    "fields": {
      "name": "bothell",
      "group": 1
    }
  },
  {
    "model": "persistent_message.tag",
    "pk": 3,
    "fields": {
      "name": "tacoma",
      "group": 1
    }
  },
  {
    "model": "persistent_message.taggroup",
    "pk": 2,
    "fields": {
      "name": "Affiliations"
    }
  },
  {
    "model": "persistent_message.tag",
    "pk": 10,
    "fields": {
      "name": "alumni",
      "group": 2
    }
  },
  {
    "model": "persistent_message.tag",
    "pk": 11,
    "fields": {
      "name": "applicant",
      "group": 2
    }
  },
  {
    "model": "persistent_message.tag",
    "pk": 12,
    "fields": {
      "name": "grad-student",
      "group": 2
    }
  },
  {
    "model": "persistent_message.tag",
    "pk": 13,
    "fields": {
      "name": "undergraduate",
      "group": 2
    }
  },
  {
    "model": "persistent_message.tag",
    "pk": 14,
    "fields": {
      "name": "gradC2",
      "group": 2
    }
  },
  {
    "model": "persistent_message.tag",
    "pk": 15,
    "fields": {
      "name": "undergraduateC2",
      "group": 2
    }
  },
  {
    "model": "persistent_message.tag",
    "pk": 16,
    "fields": {
      "name": "intl-student",
      "group": 2
    }
  },
  {
    "model": "persistent_message.tag",
    "pk": 21,
    "fields": {
      "name": "clinician",
      "group": 2
    }
  },
  {
    "model": "persistent_message.tag",
    "pk": 22,
    "fields": {
      "name": "faculty",
      "group": 2
    }
  },
  {
    "model": "persistent_message.tag",
    "pk": 23,
    "fields": {
      "name": "instructor",
      "group": 2
    }
  },
  {
    "model": "persistent_message.tag",
    "pk": 24,
    "fields": {
      "name": "staff-employee",
      "group": 2
    }
  },
  {
    "model": "persistent_message.tag",
    "pk": 25,
    "fields": {
      "name": "student-employee",
      "group": 2
    }
  }
]
